[
  {
    "variant": "Element",
    "name": "a"
  },
  {
    "variant": "Element",
    "name": "abbr"
  },
  {
    "variant": "Element",
    "name": "address"
  },
  {
    "variant": "LeafElement",
    "name": "area"
  },
  {
    "variant": "Element",
    "name": "article"
  },
  {
    "variant": "Element",
    "name": "aside"
  },
  {
    "variant": "Element",
    "name": "audio"
  },
  {
    "variant": "Element",
    "name": "b"
  },
  {
    "variant": "LeafElement",
    "name": "base"
  },
  {
    "variant": "Element",
    "name": "bdi"
  },
  {
    "variant": "Element",
    "name": "bdo"
  },
  {
    "variant": "Element",
    "name": "blockquote"
  },
  {
    "variant": "Element",
    "name": "body"
  },
  {
    "variant": "LeafElement",
    "name": "br"
  },
  {
    "variant": "Element",
    "name": "button"
  },
  {
    "variant": "Element",
    "name": "canvas"
  },
  {
    "variant": "Element",
    "name": "caption"
  },
  {
    "variant": "Element",
    "name": "cite"
  },
  {
    "variant": "Element",
    "name": "code"
  },
  {
    "variant": "Element",
    "name": "col"
  },
  {
    "variant": "Element",
    "name": "colgroup"
  },
  {
    "variant": "Element",
    "name": "data"
  },
  {
    "variant": "Element",
    "name": "datalist"
  },
  {
    "variant": "Element",
    "name": "dd"
  },
  {
    "variant": "Element",
    "name": "del"
  },
  {
    "variant": "Element",
    "name": "details"
  },
  {
    "variant": "Element",
    "name": "dfn"
  },
  {
    "variant": "Element",
    "name": "dialog"
  },
  {
    "variant": "Element",
    "name": "div"
  },
  {
    "variant": "Element",
    "name": "dl"
  },
  {
    "variant": "Element",
    "name": "dt"
  },
  {
    "variant": "Element",
    "name": "em"
  },
  {
    "variant": "Element",
    "name": "embed"
  },
  {
    "variant": "Element",
    "name": "fieldset"
  },
  {
    "variant": "Element",
    "name": "figcaption"
  },
  {
    "variant": "Element",
    "name": "figure"
  },
  {
    "variant": "Element",
    "name": "footer"
  },
  {
    "variant": "Element",
    "name": "form"
  },
  {
    "variant": "Element",
    "name": "h1"
  },
  {
    "variant": "Element",
    "name": "h2"
  },
  {
    "variant": "Element",
    "name": "h3"
  },
  {
    "variant": "Element",
    "name": "h4"
  },
  {
    "variant": "Element",
    "name": "h5"
  },
  {
    "variant": "Element",
    "name": "h6"
  },
  {
    "variant": "Element",
    "name": "header"
  },
  {
    "variant": "LeafElement",
    "name": "hr"
  },
  {
    "variant": "Element",
    "name": "i"
  },
  {
    "variant": "Element",
    "name": "iframe"
  },
  {
    "variant": "LeafElement",
    "name": "img"
  },
  {
    "variant": "LeafElement",
    "name": "input"
  },
  {
    "variant": "Element",
    "name": "ins"
  },
  {
    "variant": "Element",
    "name": "kbd"
  },
  {
    "variant": "Element",
    "name": "label"
  },
  {
    "variant": "Element",
    "name": "legend"
  },
  {
    "variant": "Element",
    "name": "li"
  },
  {
    "variant": "LeafElement",
    "name": "link"
  },
  {
    "variant": "Element",
    "name": "main"
  },
  {
    "variant": "Element",
    "name": "map"
  },
  {
    "variant": "Element",
    "name": "mark"
  },
  {
    "variant": "Element",
    "name": "math"
  },
  {
    "variant": "Element",
    "name": "menu"
  },
  {
    "variant": "Element",
    "name": "menuitem"
  },
  {
    "variant": "LeafElement",
    "name": "meta"
  },
  {
    "variant": "Element",
    "name": "meter"
  },
  {
    "variant": "Element",
    "name": "nav"
  },
  {
    "variant": "Element",
    "name": "noscript"
  },
  {
    "variant": "Element",
    "name": "object"
  },
  {
    "variant": "Element",
    "name": "ol"
  },
  {
    "variant": "Element",
    "name": "optgroup"
  },
  {
    "variant": "Element",
    "name": "option"
  },
  {
    "variant": "Element",
    "name": "output"
  },
  {
    "variant": "Element",
    "name": "p"
  },
  {
    "variant": "Element",
    "name": "param"
  },
  {
    "variant": "Element",
    "name": "picture"
  },
  {
    "variant": "Element",
    "name": "pre"
  },
  {
    "variant": "Element",
    "name": "progress"
  },
  {
    "variant": "Element",
    "name": "q"
  },
  {
    "variant": "Element",
    "name": "rp"
  },
  {
    "variant": "Element",
    "name": "rt"
  },
  {
    "variant": "Element",
    "name": "ruby"
  },
  {
    "variant": "Element",
    "name": "s"
  },
  {
    "variant": "Element",
    "name": "samp"
  },
  {
    "variant": "Element",
    "name": "section"
  },
  {
    "variant": "Element",
    "name": "select"
  },
  {
    "variant": "Element",
    "name": "small"
  },
  {
    "variant": "LeafElement",
    "name": "source"
  },
  {
    "variant": "Element",
    "name": "span"
  },
  {
    "variant": "Element",
    "name": "strong"
  },
  {
    "variant": "Element",
    "name": "sub"
  },
  {
    "variant": "Element",
    "name": "summary"
  },
  {
    "variant": "Element",
    "name": "sup"
  },
  {
    "variant": "Element",
    "name": "svg"
  },
  {
    "variant": "Element",
    "name": "table"
  },
  {
    "variant": "Element",
    "name": "tbody"
  },
  {
    "variant": "Element",
    "name": "td"
  },
  {
    "variant": "Element",
    "name": "textarea"
  },
  {
    "variant": "Element",
    "name": "tfoot"
  },
  {
    "variant": "Element",
    "name": "th"
  },
  {
    "variant": "Element",
    "name": "thead"
  },
  {
    "variant": "Element",
    "name": "time"
  },
  {
    "variant": "Element",
    "name": "title"
  },
  {
    "variant": "Element",
    "name": "tr"
  },
  {
    "variant": "LeafElement",
    "name": "track"
  },
  {
    "variant": "Element",
    "name": "u"
  },
  {
    "variant": "Element",
    "name": "ul"
  },
  {
    "variant": "Element",
    "name": "var"
  },
  {
    "variant": "Element",
    "name": "video"
  },
  {
    "variant": "Element",
    "name": "wbr"
  }
]